pyzsf/__init__.py
pyzsf/_zsf_cffi.pyd
pyzsf/pyzsf.py
pyzsf-0.1.3.dist-info/COPYING.LESSER
pyzsf-0.1.3.dist-info/METADATA
pyzsf-0.1.3.dist-info/WHEEL
pyzsf-0.1.3.dist-info/top_level.txt
pyzsf-0.1.3.dist-info/RECORD
