Metadata-Version: 2.1
Name: pyzsf
Version: 0.1.3
Summary: Model for salt intrusion through shipping locks.
Home-page: https://www.deltares.nl
Author: Jack Vreeken
Author-email: jack@vreeken.me
Maintainer: Jack Vreeken
License: LGPLv3
Keywords: zsf shipping locks salt intrusion
Platform: Windows
Platform: Linux
Platform: Mac OS-X
Platform: Unix
Classifier: Development Status :: 3 - Alpha
Classifier: Intended Audience :: Science/Research
Classifier: Intended Audience :: Information Technology
Classifier: License :: OSI Approved :: GNU Lesser General Public License v3 (LGPLv3)
Classifier: Programming Language :: Other
Classifier: Topic :: Scientific/Engineering :: GIS
Classifier: Topic :: Scientific/Engineering :: Mathematics
Classifier: Topic :: Scientific/Engineering :: Physics
Classifier: Operating System :: Microsoft :: Windows
Classifier: Operating System :: POSIX
Classifier: Operating System :: Unix
Classifier: Operating System :: MacOS
Requires-Python: >=3.6
License-File: ../../COPYING.LESSER
Requires-Dist: cffi (>=1.0.0)
